LFSR.v
module LFSR (clk, set, data, out);
    input clk, set;
    input [2:0] data;
    output reg [2:0] out;
    reg r_xor;
    always @(posedge clk) begin
        if(set)
            out <= data;
        else 
            out <= {out[1], out[0], out[2]^out[0]};
    
    end 
 
endmodule

LFSR_tb.v
`timescale 1ns/10ps
module LFSR_tb;
reg clk; 
reg set;
reg [2:0] data;
wire [2:0] out;

LFSR LFSR_tb(
    .clk(clk), 
    .set(set),
    .data(data), 
    .out(out)
);

initial begin
    clk = 0;
    set = 0;
    data = 3'b110;
end

always #50 clk = ~clk;
initial    #150 set  = 1'b1;
initial    #250 set  = 1'b0;
initial    #2000 $finish;


initial begin
    $dumpfile("LFSR.vcd");
    $dumpvars(0, LFSR_tb);
end

endmodule

LFSR.vcd
$date
	Tue May 17 16:19:42 2022
$end
$version
	Icarus Verilog
$end
$timescale
	10ps
$end
$scope module LFSR_tb $end
$scope module LFSR_tb $end
$var wire 1 ! clk $end
$var wire 3 " data [2:0] $end
$var wire 1 # set $end
$var reg 3 $ out [2:0] $end
$upscope $end
$upscope $end
$enddefinitions $end
#0
$dumpvars
bx $
0#
b110 "
0!
$end
#5000
1!
#10000
0!
#15000
b110 $
1!
1#
#20000
0!
#25000
b101 $
1!
0#
#30000
0!
#35000
b10 $
1!
#40000
0!
#45000
b100 $
1!
#50000
0!
#55000
b1 $
1!
#60000
0!
#65000
b11 $
1!
#70000
0!
#75000
b111 $
1!
#80000
0!
#85000
b110 $
1!
#90000
0!
#95000
b101 $
1!
#100000
0!
#105000
b10 $
1!
#110000
0!
#115000
b100 $
1!
#120000
0!
#125000
b1 $
1!
#130000
0!
#135000
b11 $
1!
#140000
0!
#145000
b111 $
1!
#150000
0!
#155000
b110 $
1!
#160000
0!
#165000
b101 $
1!
#170000
0!
#175000
b10 $
1!
#180000
0!
#185000
b100 $
1!
#190000
0!
#195000
b1 $
1!
